yarm/__init__.py
yarm/__main__.py
yarm/export.py
yarm/helpers.py
yarm/py.typed
yarm/queries.py
yarm/settings.py
yarm/tables.py
yarm/templates/__init__.py
yarm/templates/config_options.yaml
yarm/templates/yarm.yaml
yarm/tests_data/__init__.py
yarm/tests_data/test_config_bad_options/yarm.yaml
yarm/tests_data/test_config_bad_yaml/yarm.yaml
yarm/tests_data/test_create_tables/orders.xlsx
yarm/tests_data/test_create_tables/output/test_create_tables.xlsx
yarm/tests_data/test_create_tables/products.csv
yarm/tests_data/test_create_tables/yarm.yaml
yarm/tests_data/test_df_empty/empty.csv
yarm/tests_data/test_df_empty/empty2.csv
yarm/tests_data/test_df_empty/yarm.yaml
yarm/tests_data/test_df_input_options/tests.xlsx
yarm/tests_data/test_df_input_options/tmp.yaml
yarm/tests_data/test_df_input_options/yarm.yaml
yarm/tests_data/test_df_tables_config_options/minimum.yaml
yarm/tests_data/test_df_tables_config_options/orders.xlsx
yarm/tests_data/test_df_tables_config_options/output/dates.csv
yarm/tests_data/test_df_tables_config_options/output/orders.csv
yarm/tests_data/test_df_tables_config_options/output/pivoting.csv
yarm/tests_data/test_df_tables_config_options/output/products.csv
yarm/tests_data/test_df_tables_config_options/output/test.db
yarm/tests_data/test_df_tables_config_options/products.badext
yarm/tests_data/test_df_tables_config_options/products.csv
yarm/tests_data/test_df_tables_config_options/products_merge_missing_cols.csv
yarm/tests_data/test_df_tables_config_options/products_merge_value_error.csv
yarm/tests_data/test_df_tables_config_options/products_pivot2.csv
yarm/tests_data/test_df_tables_config_options/slugify_error.yaml
yarm/tests_data/test_df_tables_config_options/slugify_error_datetime.csv
yarm/tests_data/test_df_tables_config_options/slugify_error_pivot.csv
yarm/tests_data/test_df_tables_config_options/tests.xlsx
yarm/tests_data/test_df_tables_config_options/tmp.yaml
yarm/tests_data/test_df_tables_config_options/tmp_merge.yaml
yarm-0.2.2.dist-info/entry_points.txt
yarm-0.2.2.dist-info/LICENSE
yarm-0.2.2.dist-info/WHEEL
yarm-0.2.2.dist-info/METADATA
yarm-0.2.2.dist-info/RECORD
