Metadata-Version: 2.1
Name: yarm
Version: 0.2.2
Summary: Yarm
Home-page: https://github.com/billalive/yarm
License: Apache-2.0
Author: Bill Alive
Author-email: public+git@billalive.com
Requires-Python: >=3.8,<4.0
Classifier: Development Status :: 3 - Alpha
Classifier: License :: OSI Approved :: Apache Software License
Classifier: Programming Language :: Python :: 3
Classifier: Programming Language :: Python :: 3.8
Classifier: Programming Language :: Python :: 3.9
Classifier: Programming Language :: Python :: 3.10
Classifier: Programming Language :: Python :: 3.11
Requires-Dist: PyYAML (>=6.0,<7.0)
Requires-Dist: click (>=8.0.1)
Requires-Dist: matplotlib (>=3.5.3,<4.0.0)
Requires-Dist: nob (>=0.8.2,<0.9.0)
Requires-Dist: openpyxl (>=3.0.10,<4.0.0)
Requires-Dist: pandas (>=1.4.3,<2.0.0)
Requires-Dist: path (>=16.4.0,<17.0.0)
Requires-Dist: python-slugify (>=6.1.2,<7.0.0)
Requires-Dist: strictyaml (>=1.6.1,<2.0.0)
Project-URL: Changelog, https://github.com/billalive/yarm/releases
Project-URL: Documentation, https://yarm.readthedocs.io
Project-URL: Repository, https://github.com/billalive/yarm
